mementos/__init__.py
mementos/core.py
mementos-1.3.0.dist-info/DESCRIPTION.rst
mementos-1.3.0.dist-info/METADATA
mementos-1.3.0.dist-info/RECORD
mementos-1.3.0.dist-info/WHEEL
mementos-1.3.0.dist-info/metadata.json
mementos-1.3.0.dist-info/top_level.txt
